hypml/__init__.py
hypml/hypml.py
hypml/hypml.schema
hypml-0.0.2.dist-info/DESCRIPTION.rst
hypml-0.0.2.dist-info/METADATA
hypml-0.0.2.dist-info/RECORD
hypml-0.0.2.dist-info/WHEEL
hypml-0.0.2.dist-info/metadata.json
hypml-0.0.2.dist-info/top_level.txt
