Metadata-Version: 2.0
Name: hypml
Version: 0.0.2
Summary: A utility for loading valid Hypothesis Markup Language (.hypml) documents.
Home-page: https://github.com/HypMachine/HypML
Author: Blair Hudson
Author-email: blairhudson@me.com
License: UNKNOWN
Keywords: data,machine,learning,science,algorithm,hypml
Platform: UNKNOWN
